src/Argparser.py
src/Audio_processor.py
src/Data_analyser.py
src/Data_builder.py
src/Feature_extractor.py
src/Model_trainer.py
src/Plotter.py
src/Report_builder.py
src/__init__.py
src/config.py
src/main.py
src/utility.py
test/__init__.py
test/analyser_test.py
test/main_test.py
test/utility_test.py
fibs_reporter-0.2.8.dist-info/LICENSE.txt
fibs_reporter-0.2.8.dist-info/METADATA
fibs_reporter-0.2.8.dist-info/WHEEL
fibs_reporter-0.2.8.dist-info/entry_points.txt
fibs_reporter-0.2.8.dist-info/top_level.txt
fibs_reporter-0.2.8.dist-info/RECORD
