Metadata-Version: 2.1
Name: fibs-reporter
Version: 0.2.8
Summary: Automatically generate a pdf report containing feature importance, baseline modelling, spurious correlation detection, and more, from a single command line input
Home-page: https://github.com/m-barker/fibs-reporter/
Author: Matt Barker
License: CC BY-NC 4.0
Requires-Python: >=3.7
License-File: LICENSE.txt
Requires-Dist: fpdf2 (==2.5.5)
Requires-Dist: pandas (==1.4.3)
Requires-Dist: matplotlib (==3.5.2)
Requires-Dist: numpy (==1.23.0)
Requires-Dist: scipy (==1.8.1)
Requires-Dist: Pillow (==9.1.1)
Requires-Dist: opensmile (==2.4.1)
Requires-Dist: audiofile (==1.1.0)
Requires-Dist: sklearn (==0.0)
Requires-Dist: scikit-learn (==1.1.1)
Requires-Dist: seaborn (==0.11.2)
Requires-Dist: pydub (==0.25.1)
Requires-Dist: xgboost (==1.6.1)
